jumpstarter_driver_composite/__init__.py
jumpstarter_driver_composite/client.py
jumpstarter_driver_composite/driver.py
jumpstarter_driver_composite/driver_test.py
jumpstarter_driver_composite/py.typed
jumpstarter_driver_composite-0.7.4.dist-info/METADATA
jumpstarter_driver_composite-0.7.4.dist-info/WHEEL
jumpstarter_driver_composite-0.7.4.dist-info/entry_points.txt
jumpstarter_driver_composite-0.7.4.dist-info/RECORD
